{"directed": false, "multigraph": false, "graph": {}, "nodes": [{"id": 15917.0}, {"id": 3150.0}, {"id": 13958.0}, {"id": 2821.0}, {"id": 14071.0}, {"id": 3026.0}, {"id": 148.0}, {"id": 2062.0}, {"id": 12847.0}, {"id": 2842.0}, {"id": 2888.0}, {"id": 2240.0}, {"id": 12906.0}, {"id": 2794.0}, {"id": 9840.0}, {"id": 2765.0}, {"id": 7943.0}, {"id": 2578.0}, {"id": 18845.0}, {"id": 3179.0}, {"id": 9510.0}, {"id": 2729.0}, {"id": 8414.0}, {"id": 2601.0}, {"id": 3800.0}, {"id": 2386.0}, {"id": 13135.0}, {"id": 3092.0}, {"id": 7227.0}, {"id": 2498.0}, {"id": 4840.0}, {"id": 2353.0}, {"id": 9169.0}, {"id": 2840.0}, {"id": 4157.0}, {"id": 2279.0}, {"id": 4504.0}, {"id": 2361.0}, {"id": 13051.0}, {"id": 3129.0}, {"id": 7530.0}, {"id": 2552.0}, {"id": 2093.0}, {"id": 2122.0}, {"id": 7958.0}, {"id": 2597.0}, {"id": 2584.0}, {"id": 2195.0}, {"id": 1229.0}, {"id": 2106.0}, {"id": 613.0}, {"id": 2068.0}, {"id": 17363.0}, {"id": 3326.0}, {"id": 3586.0}, {"id": 2420.0}, {"id": 4584.0}, {"id": 2304.0}, {"id": 7286.0}, {"id": 2666.0}, {"id": 1582.0}, {"id": 867.0}, {"id": 2086.0}, {"id": 6508.0}, {"id": 2649.0}, {"id": 1576.0}, {"id": 2084.0}, {"id": 6035.0}, {"id": 2519.0}, {"id": 7260.0}, {"id": 2509.0}, {"id": 5662.0}, {"id": 2566.0}, {"id": 1495.0}, {"id": 2118.0}, {"id": 1322.0}, {"id": 2364.0}, {"id": 6396.0}, {"id": 2619.0}, {"id": 5969.0}, {"id": 2543.0}, {"id": 134.0}, {"id": 1993.0}, {"id": 2327.0}, {"id": 2132.0}, {"id": 5668.0}, {"id": 2479.0}, {"id": 5211.0}, {"id": 2357.0}, {"id": 5003.0}, {"id": 2447.0}, {"id": 1654.0}, {"id": 2117.0}, {"id": 6499.0}, {"id": 2634.0}, {"id": 59.0}, {"id": 2039.0}, {"id": 8837.0}, {"id": 2618.0}, {"id": 11293.0}, {"id": 2670.0}, {"id": 5608.0}, {"id": 2407.0}, {"id": 3411.0}, {"id": 2261.0}, {"id": 5283.0}, {"id": 2316.0}, {"id": 6662.0}, {"id": 2577.0}, {"id": 3029.0}, {"id": 2294.0}, {"id": 8155.0}, {"id": 2645.0}, {"id": 7033.0}, {"id": 2462.0}, {"id": 6874.0}, {"id": 2655.0}, {"id": 8518.0}, {"id": 2580.0}, {"id": 13208.0}, {"id": 2931.0}, {"id": 4565.0}, {"id": 2315.0}, {"id": 4569.0}, {"id": 2335.0}, {"id": 2874.0}, {"id": 2182.0}, {"id": 6643.0}, {"id": 4814.0}, {"id": 2384.0}, {"id": 8617.0}, {"id": 4627.0}, {"id": 2383.0}, {"id": 4247.0}, {"id": 2306.0}, {"id": 7177.0}, {"id": 2540.0}, {"id": 20.0}, {"id": 2040.0}, {"id": 5539.0}, {"id": 2394.0}, {"id": 7773.0}, {"id": 2573.0}, {"id": 4907.0}, {"id": 7656.0}, {"id": 2542.0}, {"id": 5361.0}, {"id": 2379.0}, {"id": 3127.0}, {"id": 2225.0}, {"id": 7096.0}, {"id": 2497.0}, {"id": 5975.0}, {"id": 2405.0}, {"id": 6412.0}, {"id": 2431.0}, {"id": 234.0}, {"id": 2034.0}, {"id": 4759.0}, {"id": 2376.0}, {"id": 7898.0}, {"id": 2529.0}, {"id": 6116.0}, {"id": 2373.0}, {"id": 6081.0}, {"id": 2421.0}, {"id": 62.0}, {"id": 1988.0}, {"id": 5468.0}, {"id": 2340.0}, {"id": 7493.0}, {"id": 2514.0}, {"id": 8216.0}, {"id": 2499.0}, {"id": 10687.0}, {"id": 2625.0}, {"id": 468.0}, {"id": 2019.0}, {"id": 3006.0}, {"id": 2232.0}, {"id": 2974.0}, {"id": 3640.0}, {"id": 2267.0}, {"id": 8939.0}, {"id": 2736.0}, {"id": 8573.0}, {"id": 11338.0}, {"id": 2988.0}, {"id": 5374.0}, {"id": 2429.0}, {"id": 685.0}, {"id": 2058.0}, {"id": 21553.0}, {"id": 3671.0}, {"id": 12899.0}, {"id": 3001.0}, {"id": 6998.0}, {"id": 2503.0}, {"id": 8171.0}, {"id": 2610.0}, {"id": 6886.0}, {"id": 7472.0}, {"id": 2481.0}, {"id": 6160.0}, {"id": 2416.0}, {"id": 9211.0}, {"id": 8411.0}, {"id": 2623.0}, {"id": 10908.0}, {"id": 2831.0}, {"id": 10684.0}, {"id": 2795.0}, {"id": 16214.0}, {"id": 3178.0}, {"id": 8723.0}, {"id": 2706.0}, {"id": 6421.0}, {"id": 2482.0}, {"id": 8436.0}, {"id": 6700.0}, {"id": 2437.0}, {"id": 5263.0}, {"id": 2362.0}, {"id": 8605.0}, {"id": 2594.0}, {"id": 11006.0}, {"id": 2942.0}, {"id": 9033.0}, {"id": 2609.0}, {"id": 6515.0}, {"id": 2422.0}, {"id": 14068.0}, {"id": 3225.0}, {"id": 6046.0}, {"id": 9015.0}, {"id": 2853.0}, {"id": 6812.0}, {"id": 2489.0}, {"id": 14151.0}, {"id": 3112.0}, {"id": 6517.0}, {"id": 6415.0}, {"id": 2493.0}, {"id": 12716.0}, {"id": 3053.0}, {"id": 6094.0}, {"id": 2404.0}, {"id": 14984.0}, {"id": 3281.0}, {"id": 7312.0}, {"id": 2541.0}, {"id": 11727.0}, {"id": 2827.0}, {"id": 8913.0}, {"id": 2652.0}, {"id": 5151.0}, {"id": 2445.0}, {"id": 13398.0}, {"id": 2849.0}, {"id": 12199.0}, {"id": 2966.0}, {"id": 2844.0}, {"id": 2258.0}, {"id": 15627.0}, {"id": 2917.0}, {"id": 9798.0}, {"id": 2631.0}, {"id": 5158.0}, {"id": 2298.0}, {"id": 10265.0}, {"id": 2700.0}, {"id": 3956.0}, {"id": 2338.0}, {"id": 5313.0}, {"id": 2366.0}, {"id": 6246.0}, {"id": 7199.0}, {"id": 2547.0}, {"id": 6433.0}, {"id": 2425.0}, {"id": 6787.0}, {"id": 2522.0}, {"id": 10356.0}, {"id": 3098.0}, {"id": 13950.0}, {"id": 3021.0}, {"id": 9266.0}, {"id": 13379.0}, {"id": 2921.0}, {"id": 6003.0}, {"id": 8338.0}, {"id": 2581.0}, {"id": 11879.0}, {"id": 3071.0}, {"id": 19056.0}, {"id": 3422.0}, {"id": 10864.0}, {"id": 2754.0}, {"id": 9412.0}, {"id": 2930.0}, {"id": 7939.0}, {"id": 5056.0}, {"id": 2067.0}, {"id": 4760.0}, {"id": 2458.0}, {"id": 15487.0}, {"id": 3448.0}, {"id": 17722.0}, {"id": 3259.0}, {"id": 6707.0}, {"id": 2561.0}, {"id": 13940.0}, {"id": 2914.0}, {"id": 5230.0}, {"id": 14001.0}, {"id": 2890.0}, {"id": 0.0}, {"id": 2066.0}, {"id": 14094.0}, {"id": 2901.0}, {"id": 3698.0}, {"id": 2251.0}, {"id": 2614.0}, {"id": 2234.0}, {"id": 344.0}, {"id": 2033.0}, {"id": 8152.0}, {"id": 2663.0}, {"id": 7264.0}, {"id": 2576.0}, {"id": 7288.0}, {"id": 2620.0}, {"id": 9669.0}, {"id": 2721.0}, {"id": 206.0}, {"id": 2055.0}, {"id": 6965.0}, {"id": 2714.0}, {"id": 10313.0}, {"id": 2705.0}, {"id": 4536.0}, {"id": 2308.0}, {"id": 35.0}, {"id": 2063.0}, {"id": 8540.0}, {"id": 2568.0}, {"id": 3668.0}, {"id": 2227.0}, {"id": 7634.0}, {"id": 2611.0}, {"id": 4924.0}, {"id": 2365.0}, {"id": 4519.0}, {"id": 2370.0}, {"id": 1929.0}, {"id": 2198.0}, {"id": 4676.0}, {"id": 2371.0}, {"id": 4554.0}, {"id": 2397.0}, {"id": 2064.0}, {"id": 3190.0}, {"id": 2318.0}, {"id": 113.0}, {"id": 3460.0}, {"id": 2330.0}, {"id": 6675.0}, {"id": 4252.0}, {"id": 3754.0}, {"id": 2341.0}, {"id": 1015.0}, {"id": 2100.0}, {"id": 3794.0}, {"id": 530.0}, {"id": 3940.0}, {"id": 2455.0}, {"id": 240.0}, {"id": 2014.0}, {"id": 8452.0}, {"id": 2686.0}, {"id": NaN}, {"id": NaN}, {"id": 10950.0}, {"id": 2703.0}, {"id": 6032.0}, {"id": 2659.0}, {"id": 429.0}, {"id": 2071.0}, {"id": 4551.0}, {"id": 2347.0}, {"id": 5117.0}, {"id": 2488.0}, {"id": 2480.0}, {"id": 2244.0}, {"id": 2278.0}, {"id": 1675.0}, {"id": 2124.0}, {"id": 778.0}, {"id": 105.0}, {"id": 2001.0}, {"id": 81.0}, {"id": 1059.0}, {"id": 2127.0}, {"id": 4887.0}, {"id": 2495.0}, {"id": 398.0}, {"id": 974.0}, {"id": 2628.0}, {"id": 5710.0}, {"id": 2363.0}, {"id": 2803.0}, {"id": 2243.0}, {"id": 301.0}, {"id": 2095.0}, {"id": 1779.0}, {"id": 2253.0}, {"id": 78.0}, {"id": 2242.0}, {"id": 4700.0}, {"id": 2627.0}, {"id": 8217.0}, {"id": 2638.0}, {"id": 7361.0}, {"id": 2556.0}, {"id": 244.0}, {"id": 1158.0}, {"id": 2169.0}, {"id": 1355.0}, {"id": 2143.0}, {"id": 385.0}, {"id": 151.0}, {"id": 2042.0}, {"id": 38.0}, {"id": 2048.0}, {"id": 89.0}, {"id": 360.0}, {"id": 2078.0}, {"id": 1972.0}, {"id": 2155.0}, {"id": 421.0}, {"id": 2056.0}, {"id": 26.0}, {"id": 2051.0}], "links": [{"source": 15917.0, "target": 3150.0}, {"source": 13958.0, "target": 2821.0}, {"source": 2821.0, "target": 8617.0}, {"source": 14071.0, "target": 3026.0}, {"source": 148.0, "target": 2062.0}, {"source": 2062.0, "target": 398.0}, {"source": 12847.0, "target": 2842.0}, {"source": 2888.0, "target": 2240.0}, {"source": 12906.0, "target": 2794.0}, {"source": 9840.0, "target": 2765.0}, {"source": 7943.0, "target": 2578.0}, {"source": 2578.0, "target": 8573.0}, {"source": 18845.0, "target": 3179.0}, {"source": 9510.0, "target": 2729.0}, {"source": 8414.0, "target": 2601.0}, {"source": 3800.0, "target": 2386.0}, {"source": 13135.0, "target": 3092.0}, {"source": 7227.0, "target": 2498.0}, {"source": 4840.0, "target": 2353.0}, {"source": 9169.0, "target": 2840.0}, {"source": 4157.0, "target": 2279.0}, {"source": 4504.0, "target": 2361.0}, {"source": 13051.0, "target": 3129.0}, {"source": 7530.0, "target": 2552.0}, {"source": 2093.0, "target": 2122.0}, {"source": 7958.0, "target": 2597.0}, {"source": 2584.0, "target": 2195.0}, {"source": 1229.0, "target": 2106.0}, {"source": 2106.0, "target": 1582.0}, {"source": 613.0, "target": 2068.0}, {"source": 17363.0, "target": 3326.0}, {"source": 3586.0, "target": 2420.0}, {"source": 4584.0, "target": 2304.0}, {"source": 7286.0, "target": 2666.0}, {"source": 867.0, "target": 2086.0}, {"source": 6508.0, "target": 2649.0}, {"source": 1576.0, "target": 2084.0}, {"source": 6035.0, "target": 2519.0}, {"source": 2519.0, "target": 6675.0}, {"source": 7260.0, "target": 2509.0}, {"source": 5662.0, "target": 2566.0}, {"source": 1495.0, "target": 2118.0}, {"source": 1322.0, "target": 2364.0}, {"source": 6396.0, "target": 2619.0}, {"source": 5969.0, "target": 2543.0}, {"source": 134.0, "target": 1993.0}, {"source": 2327.0, "target": 2132.0}, {"source": 2327.0, "target": 4252.0}, {"source": 5668.0, "target": 2479.0}, {"source": 5211.0, "target": 2357.0}, {"source": 5003.0, "target": 2447.0}, {"source": 1654.0, "target": 2117.0}, {"source": 6499.0, "target": 2634.0}, {"source": 59.0, "target": 2039.0}, {"source": 8837.0, "target": 2618.0}, {"source": 11293.0, "target": 2670.0}, {"source": 5608.0, "target": 2407.0}, {"source": 3411.0, "target": 2261.0}, {"source": 2261.0, "target": 2974.0}, {"source": 5283.0, "target": 2316.0}, {"source": 2316.0, "target": 4907.0}, {"source": 6662.0, "target": 2577.0}, {"source": 3029.0, "target": 2294.0}, {"source": 8155.0, "target": 2645.0}, {"source": 2645.0, "target": 9211.0}, {"source": 7033.0, "target": 2462.0}, {"source": 2462.0, "target": 6246.0}, {"source": 6874.0, "target": 2655.0}, {"source": 8518.0, "target": 2580.0}, {"source": 2580.0, "target": 6643.0}, {"source": 13208.0, "target": 2931.0}, {"source": 4565.0, "target": 2315.0}, {"source": 4569.0, "target": 2335.0}, {"source": 2874.0, "target": 2182.0}, {"source": 2874.0, "target": 9266.0}, {"source": 2182.0, "target": 2067.0}, {"source": 4814.0, "target": 2384.0}, {"source": 2384.0, "target": 5056.0}, {"source": 4627.0, "target": 2383.0}, {"source": 4247.0, "target": 2306.0}, {"source": 7177.0, "target": 2540.0}, {"source": 20.0, "target": 2040.0}, {"source": 5539.0, "target": 2394.0}, {"source": 7773.0, "target": 2573.0}, {"source": 7656.0, "target": 2542.0}, {"source": 5361.0, "target": 2379.0}, {"source": 3127.0, "target": 2225.0}, {"source": 7096.0, "target": 2497.0}, {"source": 5975.0, "target": 2405.0}, {"source": 6412.0, "target": 2431.0}, {"source": 2431.0, "target": 6003.0}, {"source": 234.0, "target": 2034.0}, {"source": 2034.0, "target": 89.0}, {"source": 4759.0, "target": 2376.0}, {"source": 7898.0, "target": 2529.0}, {"source": 2529.0, "target": 8436.0}, {"source": 6116.0, "target": 2373.0}, {"source": 2373.0, "target": 6046.0}, {"source": 6081.0, "target": 2421.0}, {"source": 62.0, "target": 1988.0}, {"source": 5468.0, "target": 2340.0}, {"source": 7493.0, "target": 2514.0}, {"source": 8216.0, "target": 2499.0}, {"source": 2499.0, "target": 6886.0}, {"source": 10687.0, "target": 2625.0}, {"source": 468.0, "target": 2019.0}, {"source": 3006.0, "target": 2232.0}, {"source": 3640.0, "target": 2267.0}, {"source": 8939.0, "target": 2736.0}, {"source": 11338.0, "target": 2988.0}, {"source": 5374.0, "target": 2429.0}, {"source": 685.0, "target": 2058.0}, {"source": 21553.0, "target": 3671.0}, {"source": 12899.0, "target": 3001.0}, {"source": 6998.0, "target": 2503.0}, {"source": 2503.0, "target": 5230.0}, {"source": 8171.0, "target": 2610.0}, {"source": 7472.0, "target": 2481.0}, {"source": 6160.0, "target": 2416.0}, {"source": 8411.0, "target": 2623.0}, {"source": 10908.0, "target": 2831.0}, {"source": 10684.0, "target": 2795.0}, {"source": 16214.0, "target": 3178.0}, {"source": 8723.0, "target": 2706.0}, {"source": 6421.0, "target": 2482.0}, {"source": 2482.0, "target": 6517.0}, {"source": 6700.0, "target": 2437.0}, {"source": 5263.0, "target": 2362.0}, {"source": 8605.0, "target": 2594.0}, {"source": 11006.0, "target": 2942.0}, {"source": 9033.0, "target": 2609.0}, {"source": 6515.0, "target": 2422.0}, {"source": 14068.0, "target": 3225.0}, {"source": 9015.0, "target": 2853.0}, {"source": 6812.0, "target": 2489.0}, {"source": 14151.0, "target": 3112.0}, {"source": 6415.0, "target": 2493.0}, {"source": 12716.0, "target": 3053.0}, {"source": 6094.0, "target": 2404.0}, {"source": 14984.0, "target": 3281.0}, {"source": 7312.0, "target": 2541.0}, {"source": 2541.0, "target": 7939.0}, {"source": 11727.0, "target": 2827.0}, {"source": 8913.0, "target": 2652.0}, {"source": 5151.0, "target": 2445.0}, {"source": 13398.0, "target": 2849.0}, {"source": 12199.0, "target": 2966.0}, {"source": 2844.0, "target": 2258.0}, {"source": 15627.0, "target": 2917.0}, {"source": 9798.0, "target": 2631.0}, {"source": 5158.0, "target": 2298.0}, {"source": 10265.0, "target": 2700.0}, {"source": 3956.0, "target": 2338.0}, {"source": 5313.0, "target": 2366.0}, {"source": 7199.0, "target": 2547.0}, {"source": 6433.0, "target": 2425.0}, {"source": 6787.0, "target": 2522.0}, {"source": 10356.0, "target": 3098.0}, {"source": 13950.0, "target": 3021.0}, {"source": 3021.0, "target": 2278.0}, {"source": 13379.0, "target": 2921.0}, {"source": 8338.0, "target": 2581.0}, {"source": 11879.0, "target": 3071.0}, {"source": 19056.0, "target": 3422.0}, {"source": 10864.0, "target": 2754.0}, {"source": 9412.0, "target": 2930.0}, {"source": 2067.0, "target": 244.0}, {"source": 4760.0, "target": 2458.0}, {"source": 15487.0, "target": 3448.0}, {"source": 17722.0, "target": 3259.0}, {"source": 6707.0, "target": 2561.0}, {"source": 13940.0, "target": 2914.0}, {"source": 14001.0, "target": 2890.0}, {"source": 0.0, "target": 2066.0}, {"source": 0.0, "target": 2064.0}, {"source": 2066.0, "target": 113.0}, {"source": 14094.0, "target": 2901.0}, {"source": 3698.0, "target": 2251.0}, {"source": 2614.0, "target": 2234.0}, {"source": 344.0, "target": 2033.0}, {"source": 8152.0, "target": 2663.0}, {"source": 7264.0, "target": 2576.0}, {"source": 7288.0, "target": 2620.0}, {"source": 9669.0, "target": 2721.0}, {"source": 206.0, "target": 2055.0}, {"source": 6965.0, "target": 2714.0}, {"source": 10313.0, "target": 2705.0}, {"source": 4536.0, "target": 2308.0}, {"source": 35.0, "target": 2063.0}, {"source": 8540.0, "target": 2568.0}, {"source": 3668.0, "target": 2227.0}, {"source": 7634.0, "target": 2611.0}, {"source": 4924.0, "target": 2365.0}, {"source": 4519.0, "target": 2370.0}, {"source": 1929.0, "target": 2198.0}, {"source": 4676.0, "target": 2371.0}, {"source": 4554.0, "target": 2397.0}, {"source": 2064.0, "target": 530.0}, {"source": 2064.0, "target": 81.0}, {"source": 3190.0, "target": 2318.0}, {"source": 3460.0, "target": 2330.0}, {"source": 2330.0, "target": 3794.0}, {"source": 3754.0, "target": 2341.0}, {"source": 1015.0, "target": 2100.0}, {"source": 3940.0, "target": 2455.0}, {"source": 240.0, "target": 2014.0}, {"source": 8452.0, "target": 2686.0}, {"source": NaN, "target": NaN}, {"source": 10950.0, "target": 2703.0}, {"source": 6032.0, "target": 2659.0}, {"source": 429.0, "target": 2071.0}, {"source": 4551.0, "target": 2347.0}, {"source": 5117.0, "target": 2488.0}, {"source": 2480.0, "target": 2244.0}, {"source": 2244.0, "target": 778.0}, {"source": 1675.0, "target": 2124.0}, {"source": 105.0, "target": 2001.0}, {"source": 1059.0, "target": 2127.0}, {"source": 4887.0, "target": 2495.0}, {"source": 974.0, "target": 2628.0}, {"source": 5710.0, "target": 2363.0}, {"source": 2803.0, "target": 2243.0}, {"source": 301.0, "target": 2095.0}, {"source": 2095.0, "target": 385.0}, {"source": 1779.0, "target": 2253.0}, {"source": 78.0, "target": 2242.0}, {"source": 4700.0, "target": 2627.0}, {"source": 8217.0, "target": 2638.0}, {"source": 7361.0, "target": 2556.0}, {"source": 1158.0, "target": 2169.0}, {"source": 1355.0, "target": 2143.0}, {"source": 151.0, "target": 2042.0}, {"source": 38.0, "target": 2048.0}, {"source": 360.0, "target": 2078.0}, {"source": 1972.0, "target": 2155.0}, {"source": 421.0, "target": 2056.0}, {"source": 26.0, "target": 2051.0}]}
